Metadata-Version: 2.1
Name: pyteiser
Version: 0.0.1
Summary: Python implementation of TEISER
Home-page: https://github.com/goodarzilab/pyteiser
Author: Matvei Khoroshkin, Hani Goodarzi
Author-email: khorms21@gmail.com
License: UNKNOWN
Platform: UNKNOWN
Classifier: Programming Language :: Python :: 3
Classifier: License :: OSI Approved :: MIT License
Classifier: Operating System :: OS Independent
Requires-Dist: numba (>=0.50.1)
Requires-Dist: numpy (>=1.19.1)
Requires-Dist: pandas (>=1.1.1)
